EMP/__init__.py
EMP/metrics.py
EMP_PY-2.0.4.dist-info/LICENSE
EMP_PY-2.0.4.dist-info/METADATA
EMP_PY-2.0.4.dist-info/WHEEL
EMP_PY-2.0.4.dist-info/top_level.txt
EMP_PY-2.0.4.dist-info/RECORD
