Metadata-Version: 2.1
Name: EMP-PY
Version: 2.0.4
Summary: Functions for estimating EMP (Expected Maximum Profit Measure) in Credit Risk Scoring and Customer Churn Prediction, according to Verbraken et al (2013, 2014).
Home-page: https://github.com/Banking-Analytics-Lab/EMP-Py
Author: Cristián Bravo
Author-email: cbravoro@uwo.ca
Classifier: Programming Language :: Python :: 3
Classifier: License :: OSI Approved :: GNU General Public License v3 or later (GPLv3+)
Classifier: Operating System :: OS Independent
Requires-Python: >=3.8
License-File: LICENSE
Requires-Dist: numpy
Requires-Dist: pandas
Requires-Dist: scipy
Requires-Dist: scikit-learn
